awive-3.3.1.dist-info/METADATA
awive-3.3.1.dist-info/WHEEL
awive-3.3.1.dist-info/entry_points.txt
awive-3.3.1.dist-info/licenses/LICENSE
awive/__init__.py
awive/__main__.py
awive/algorithms/__init__.py
awive/algorithms/image_velocimetry.py
awive/algorithms/otv.py
awive/algorithms/sti.py
awive/algorithms/water_flow.py
awive/algorithms/water_level_hist.py
awive/config.py
awive/exceptions.py
awive/loader.py
awive/plots.py
awive/preprocess/__init__.py
awive/preprocess/correct_image.py
awive/preprocess/imageprep.py
awive/py.typed
awive/tests/test_algorithms/test_water_flow.py
awive/tests/test_config.py
awive/tools/__init__.py
awive/tools/to_video.py
awive/video.py
examples/__init__.py
examples/basic/__init__.py
examples/basic/__main__.py
examples/basic/images/.gitkeep
examples/datasets/artificial/images/.gitkeep
examples/datasets/river-brenta/images/.gitkeep
experiments/__init__.py
experiments/otv.py
experiments/process.py
awive-3.3.1.dist-info/RECORD
