Metadata-Version: 2.1
Name: awive
Version: 3.3.1
Summary: Adaptive Water Image Velocimetry
Author-Email: "Joseph P." <joseph.pena.q@gmail.com>
Requires-Python: <=3.13.7,>=3.9
Requires-Dist: numpy<1.27,>=1.26
Requires-Dist: opencv-python<4.12,>=4.6
Requires-Dist: pydantic>=2.7.4
